util_methods/__init__.py
util_methods/main.py
util_methods_test_io-0.3.0.dist-info/METADATA
util_methods_test_io-0.3.0.dist-info/WHEEL
util_methods_test_io-0.3.0.dist-info/top_level.txt
util_methods_test_io-0.3.0.dist-info/RECORD
